async_s3/__about__.py
async_s3/__init__.py
async_s3/group_by_prefix.py
async_s3/main.py
async_s3/s3_bucket_objects.py
async_s3-2.2.1.dist-info/METADATA
async_s3-2.2.1.dist-info/WHEEL
async_s3-2.2.1.dist-info/entry_points.txt
async_s3-2.2.1.dist-info/licenses/LICENSE.txt
async_s3-2.2.1.dist-info/RECORD
