Metadata-Version: 2.3
Name: async-s3
Version: 2.2.1
Summary: S3 Bucket helper utils. Async list objects by folders.
Project-URL: Homepage, https://andgineer.github.io/async-s3/
Project-URL: Documentation, https://andgineer.github.io/async-s3/
Author-email: Andrey Sorokin <andrey@sorokin.engineer>
License: Copyright (c) 2024 Andrey Sorokin <andrey@sorokin.engineer>
License-File: LICENSE.txt
Keywords: async,aws,bucket,folders,list-objects,s3
Classifier: License :: OSI Approved :: MIT License
Classifier: Operating System :: OS Independent
Classifier: Programming Language :: Python :: 3
Requires-Python: >=3.9
Requires-Dist: aiobotocore
Requires-Dist: boto3
Requires-Dist: click
Requires-Dist: rich-click
